<archimate:ArchimateDiagramModel
    xmlns:xsi="http://www.w3.org/2001/XMLSchema-instance"
    xmlns:archimate="http://www.archimatetool.com/archimate"
    name="20170511 Gebruik iWMO berichten"
    id="e541a817">
  <children
      xsi:type="archimate:DiagramModelArchimateObject"
      id="3512e3e3">
    <sourceConnections
        xsi:type="archimate:DiagramModelArchimateConnection"
        id="ad9fb1e2"
        source="3512e3e3"
        target="a03ebcf2">
      <archimateRelationship
          xsi:type="archimate:AssignmentRelationship"
          href="AssignmentRelationship_197c2911.xml#197c2911"/>
    </sourceConnections>
    <bounds
        x="172"
        y="68"
        width="120"
        height="55"/>
    <archimateElement
        xsi:type="archimate:BusinessActor"
        href="BusinessActor_8f7dbf85.xml#8f7dbf85"/>
  </children>
  <children
      xsi:type="archimate:DiagramModelArchimateObject"
      id="7df800b7">
    <sourceConnections
        xsi:type="archimate:DiagramModelArchimateConnection"
        id="842e8e08"
        source="7df800b7"
        target="af29c11c">
      <archimateRelationship
          xsi:type="archimate:AssignmentRelationship"
          href="AssignmentRelationship_c9a69b3f.xml#c9a69b3f"/>
    </sourceConnections>
    <sourceConnections
        xsi:type="archimate:DiagramModelArchimateConnection"
        id="8f31bff5"
        source="7df800b7"
        target="44ac70ef">
      <archimateRelationship
          xsi:type="archimate:AccessRelationship"
          href="AccessRelationship_e44246ad.xml#e44246ad"/>
    </sourceConnections>
    <sourceConnections
        xsi:type="archimate:DiagramModelArchimateConnection"
        id="ab6932a7"
        source="7df800b7"
        target="2e92111a">
      <archimateRelationship
          xsi:type="archimate:AccessRelationship"
          href="AccessRelationship_9ce7917e.xml#9ce7917e"/>
    </sourceConnections>
    <bounds
        x="612"
        y="68"
        width="120"
        height="55"/>
    <archimateElement
        xsi:type="archimate:BusinessActor"
        href="BusinessActor_71cd81be.xml#71cd81be"/>
  </children>
  <children
      xsi:type="archimate:DiagramModelArchimateObject"
      id="e3baeb29">
    <sourceConnections
        xsi:type="archimate:DiagramModelArchimateConnection"
        id="81a0d04e"
        source="e3baeb29"
        target="6525c890">
      <archimateRelationship
          xsi:type="archimate:AssignmentRelationship"
          href="AssignmentRelationship_79e848d7.xml#79e848d7"/>
    </sourceConnections>
    <sourceConnections
        xsi:type="archimate:DiagramModelArchimateConnection"
        id="ffcdfd36"
        source="e3baeb29"
        target="44ac70ef">
      <archimateRelationship
          xsi:type="archimate:AccessRelationship"
          href="AccessRelationship_d2bf59b9.xml#d2bf59b9"/>
    </sourceConnections>
    <sourceConnections
        xsi:type="archimate:DiagramModelArchimateConnection"
        id="c29c43f8"
        source="e3baeb29"
        target="2e92111a">
      <archimateRelationship
          xsi:type="archimate:AccessRelationship"
          href="AccessRelationship_8088dd51.xml#8088dd51"/>
    </sourceConnections>
    <bounds
        x="324"
        y="68"
        width="120"
        height="55"/>
    <archimateElement
        xsi:type="archimate:BusinessActor"
        href="BusinessActor_280eee9f.xml#280eee9f"/>
  </children>
  <children
      xsi:type="archimate:DiagramModelArchimateObject"
      id="a03ebcf2"
      targetConnections="2795813c ad9fb1e2">
    <bounds
        x="172"
        y="144"
        width="120"
        height="55"/>
    <archimateElement
        xsi:type="archimate:BusinessFunction"
        href="BusinessFunction_36d50bc5.xml#36d50bc5"/>
  </children>
  <children
      xsi:type="archimate:DiagramModelArchimateObject"
      id="6525c890"
      targetConnections="66ee88e5 81a0d04e">
    <bounds
        x="324"
        y="144"
        width="120"
        height="55"/>
    <archimateElement
        xsi:type="archimate:BusinessFunction"
        href="BusinessFunction_2113e184.xml#2113e184"/>
  </children>
  <children
      xsi:type="archimate:DiagramModelArchimateObject"
      id="af29c11c"
      targetConnections="b5beda57 842e8e08">
    <bounds
        x="612"
        y="144"
        width="120"
        height="55"/>
    <archimateElement
        xsi:type="archimate:BusinessFunction"
        href="BusinessFunction_28bcdba1.xml#28bcdba1"/>
  </children>
  <children
      xsi:type="archimate:DiagramModelArchimateObject"
      id="c64311bb"
      targetConnections="b848c2e0">
    <sourceConnections
        xsi:type="archimate:DiagramModelArchimateConnection"
        id="66ee88e5"
        source="c64311bb"
        target="6525c890">
      <archimateRelationship
          xsi:type="archimate:ServingRelationship"
          href="ServingRelationship_ab95e864.xml#ab95e864"/>
    </sourceConnections>
    <sourceConnections
        xsi:type="archimate:DiagramModelArchimateConnection"
        id="b380f628"
        source="c64311bb"
        target="705924ed">
      <archimateRelationship
          xsi:type="archimate:RealizationRelationship"
          href="RealizationRelationship_44173ff5.xml#44173ff5"/>
    </sourceConnections>
    <bounds
        x="324"
        y="240"
        width="120"
        height="55"/>
    <archimateElement
        xsi:type="archimate:ApplicationComponent"
        href="ApplicationComponent_3873da5d.xml#3873da5d"/>
  </children>
  <children
      xsi:type="archimate:DiagramModelArchimateObject"
      id="5601bdca"
      targetConnections="be875a4e">
    <sourceConnections
        xsi:type="archimate:DiagramModelArchimateConnection"
        id="b5beda57"
        source="5601bdca"
        target="af29c11c">
      <archimateRelationship
          xsi:type="archimate:ServingRelationship"
          href="ServingRelationship_067b6c06.xml#067b6c06"/>
    </sourceConnections>
    <sourceConnections
        xsi:type="archimate:DiagramModelArchimateConnection"
        id="bf702c57"
        source="5601bdca"
        target="a2292b8e">
      <archimateRelationship
          xsi:type="archimate:RealizationRelationship"
          href="RealizationRelationship_a2413a48.xml#a2413a48"/>
    </sourceConnections>
    <bounds
        x="612"
        y="240"
        width="120"
        height="55"/>
    <archimateElement
        xsi:type="archimate:ApplicationComponent"
        href="ApplicationComponent_49bfbe20.xml#49bfbe20"/>
  </children>
  <children
      xsi:type="archimate:DiagramModelArchimateObject"
      id="841bd840">
    <sourceConnections
        xsi:type="archimate:DiagramModelArchimateConnection"
        id="2795813c"
        source="841bd840"
        target="a03ebcf2">
      <archimateRelationship
          xsi:type="archimate:ServingRelationship"
          href="ServingRelationship_befcff25.xml#befcff25"/>
    </sourceConnections>
    <bounds
        x="172"
        y="240"
        width="120"
        height="55"/>
    <archimateElement
        xsi:type="archimate:ApplicationComponent"
        href="ApplicationComponent_49bfbe20.xml#49bfbe20"/>
  </children>
  <children
      xsi:type="archimate:DiagramModelArchimateObject"
      id="44ac70ef"
      targetConnections="ffcdfd36 8f31bff5">
    <bounds
        x="468"
        y="36"
        width="120"
        height="55"/>
    <archimateElement
        xsi:type="archimate:BusinessObject"
        href="BusinessObject_8689f965.xml#8689f965"/>
  </children>
  <children
      xsi:type="archimate:DiagramModelArchimateObject"
      id="2e92111a"
      targetConnections="c29c43f8 ab6932a7">
    <bounds
        x="468"
        y="96"
        width="120"
        height="55"/>
    <archimateElement
        xsi:type="archimate:BusinessObject"
        href="BusinessObject_8fe33ee0.xml#8fe33ee0"/>
  </children>
  <children
      xsi:type="archimate:DiagramModelArchimateObject"
      id="a2292b8e"
      targetConnections="bf702c57">
    <sourceConnections
        xsi:type="archimate:DiagramModelArchimateConnection"
        id="b848c2e0"
        source="a2292b8e"
        target="c64311bb">
      <archimateRelationship
          xsi:type="archimate:ServingRelationship"
          href="ServingRelationship_a8c77758.xml#a8c77758"/>
    </sourceConnections>
    <bounds
        x="468"
        y="216"
        width="120"
        height="55"/>
    <archimateElement
        xsi:type="archimate:ApplicationService"
        href="ApplicationService_d6ad0932.xml#d6ad0932"/>
  </children>
  <children
      xsi:type="archimate:DiagramModelArchimateObject"
      id="705924ed"
      targetConnections="b380f628">
    <sourceConnections
        xsi:type="archimate:DiagramModelArchimateConnection"
        id="be875a4e"
        source="705924ed"
        target="5601bdca">
      <archimateRelationship
          xsi:type="archimate:ServingRelationship"
          href="ServingRelationship_8a09e13c.xml#8a09e13c"/>
    </sourceConnections>
    <bounds
        x="468"
        y="276"
        width="120"
        height="55"/>
    <archimateElement
        xsi:type="archimate:ApplicationService"
        href="ApplicationService_37f59066.xml#37f59066"/>
  </children>
</archimate:ArchimateDiagramModel>
