<archimate:ArchimateDiagramModel
    xmlns:xsi="http://www.w3.org/2001/XMLSchema-instance"
    xmlns:archimate="http://www.archimatetool.com/archimate"
    name="Informatiestromen MO/BW, doelsituatie II"
    id="5c47e765">
  <children
      xsi:type="archimate:DiagramModelArchimateObject"
      id="a8fce440">
    <sourceConnections
        xsi:type="archimate:DiagramModelArchimateConnection"
        id="c2df007b"
        source="a8fce440"
        target="ef0b93d3">
      <archimateRelationship
          xsi:type="archimate:AssignmentRelationship"
          href="AssignmentRelationship_fc05e040.xml#fc05e040"/>
    </sourceConnections>
    <bounds
        x="1044"
        y="564"
        width="120"
        height="55"/>
    <archimateElement
        xsi:type="archimate:BusinessRole"
        href="BusinessRole_db3fbb4a.xml#db3fbb4a"/>
  </children>
  <children
      xsi:type="archimate:DiagramModelArchimateObject"
      id="757afa9b">
    <sourceConnections
        xsi:type="archimate:DiagramModelArchimateConnection"
        id="ec1b4be6"
        source="757afa9b"
        target="64d47777">
      <archimateRelationship
          xsi:type="archimate:AssignmentRelationship"
          href="AssignmentRelationship_fba32ba5.xml#fba32ba5"/>
    </sourceConnections>
    <bounds
        x="72"
        y="144"
        width="120"
        height="55"/>
    <archimateElement
        xsi:type="archimate:BusinessActor"
        href="BusinessActor_480d6ee4.xml#480d6ee4"/>
  </children>
  <children
      xsi:type="archimate:DiagramModelArchimateObject"
      id="3e0a740a">
    <sourceConnections
        xsi:type="archimate:DiagramModelArchimateConnection"
        id="2acfde97"
        source="3e0a740a"
        target="20feb05c">
      <bendpoints
          startX="132"
          startY="-3"
          endX="-120"
          endY="9"/>
      <archimateRelationship
          xsi:type="archimate:AccessRelationship"
          href="AccessRelationship_bf3bdfda.xml#bf3bdfda"/>
    </sourceConnections>
    <sourceConnections
        xsi:type="archimate:DiagramModelArchimateConnection"
        id="d73efcd3"
        source="3e0a740a"
        target="a2fc3905">
      <archimateRelationship
          xsi:type="archimate:AccessRelationship"
          href="AccessRelationship_e25170e9.xml#e25170e9"/>
    </sourceConnections>
    <sourceConnections
        xsi:type="archimate:DiagramModelArchimateConnection"
        id="af8fd987"
        source="3e0a740a"
        target="5abf0169">
      <archimateRelationship
          xsi:type="archimate:AccessRelationship"
          href="AccessRelationship_b79de7c5.xml#b79de7c5"/>
    </sourceConnections>
    <sourceConnections
        xsi:type="archimate:DiagramModelArchimateConnection"
        id="662a0f8e"
        source="3e0a740a"
        target="34f131d7">
      <bendpoints
          startX="252"
          startY="21"
          endY="-75"/>
      <archimateRelationship
          xsi:type="archimate:AccessRelationship"
          href="AccessRelationship_3bcc59c8.xml#3bcc59c8"/>
    </sourceConnections>
    <sourceConnections
        xsi:type="archimate:DiagramModelArchimateConnection"
        id="edf6af78"
        source="3e0a740a"
        target="bac485e3">
      <bendpoints
          startX="-156"
          startY="-3"
          endY="51"/>
      <archimateRelationship
          xsi:type="archimate:AccessRelationship"
          href="AccessRelationship_1df86a2e.xml#1df86a2e"/>
    </sourceConnections>
    <bounds
        x="516"
        y="348"
        width="120"
        height="55"/>
    <archimateElement
        xsi:type="archimate:BusinessActor"
        href="BusinessActor_f9c152ce.xml#f9c152ce"/>
  </children>
  <children
      xsi:type="archimate:DiagramModelArchimateObject"
      id="34f131d7"
      targetConnections="70869a1a 662a0f8e">
    <bounds
        x="768"
        y="444"
        width="120"
        height="55"/>
    <archimateElement
        xsi:type="archimate:BusinessObject"
        href="BusinessObject_a687926d.xml#a687926d"/>
  </children>
  <children
      xsi:type="archimate:DiagramModelArchimateObject"
      id="64d47777"
      targetConnections="ec1b4be6">
    <sourceConnections
        xsi:type="archimate:DiagramModelArchimateConnection"
        id="ec8dd605"
        source="64d47777"
        target="db8eb96a">
      <archimateRelationship
          xsi:type="archimate:AssignmentRelationship"
          href="AssignmentRelationship_bd886e60.xml#bd886e60"/>
    </sourceConnections>
    <bounds
        x="228"
        y="144"
        width="120"
        height="55"/>
    <archimateElement
        xsi:type="archimate:BusinessRole"
        href="BusinessRole_b36617a0.xml#b36617a0"/>
  </children>
  <children
      xsi:type="archimate:DiagramModelArchimateObject"
      id="ef0b93d3"
      targetConnections="c2df007b">
    <sourceConnections
        xsi:type="archimate:DiagramModelArchimateConnection"
        id="70869a1a"
        source="ef0b93d3"
        target="34f131d7">
      <bendpoints
          startX="-36"
          startY="-111"
          endX="96"
          endY="9"/>
      <archimateRelationship
          xsi:type="archimate:AccessRelationship"
          href="AccessRelationship_c8e9fe7c.xml#c8e9fe7c"/>
    </sourceConnections>
    <sourceConnections
        xsi:type="archimate:DiagramModelArchimateConnection"
        id="2c543b19"
        source="ef0b93d3"
        target="57b9b81b">
      <archimateRelationship
          xsi:type="archimate:AccessRelationship"
          href="AccessRelationship_4c70b8e5.xml#4c70b8e5"/>
    </sourceConnections>
    <sourceConnections
        xsi:type="archimate:DiagramModelArchimateConnection"
        id="72cfcf8c"
        source="ef0b93d3"
        target="bc8ad119">
      <archimateRelationship
          xsi:type="archimate:AccessRelationship"
          href="AccessRelationship_2e7ab407.xml#2e7ab407"/>
    </sourceConnections>
    <sourceConnections
        xsi:type="archimate:DiagramModelArchimateConnection"
        id="3b25227f"
        source="ef0b93d3"
        target="f7d74d55">
      <archimateRelationship
          xsi:type="archimate:AccessRelationship"
          href="AccessRelationship_1d8050ab.xml#1d8050ab"/>
    </sourceConnections>
    <bounds
        x="900"
        y="564"
        width="120"
        height="55"/>
    <archimateElement
        xsi:type="archimate:BusinessFunction"
        href="BusinessFunction_68c4109c.xml#68c4109c"/>
  </children>
  <children
      xsi:type="archimate:DiagramModelArchimateObject"
      id="db8eb96a"
      targetConnections="ec8dd605">
    <sourceConnections
        xsi:type="archimate:DiagramModelArchimateConnection"
        id="46dbc141"
        source="db8eb96a"
        target="c9048919">
      <bendpoints
          startX="36"
          startY="297"
          endX="-96"
          endY="-3"/>
      <archimateRelationship
          xsi:type="archimate:AccessRelationship"
          href="AccessRelationship_0eb7ae3f.xml#0eb7ae3f"/>
    </sourceConnections>
    <sourceConnections
        xsi:type="archimate:DiagramModelArchimateConnection"
        id="87508bf8"
        source="db8eb96a"
        target="7e8c4fa1">
      <bendpoints
          startY="369"
          endX="-132"
          endY="-3"/>
      <archimateRelationship
          xsi:type="archimate:AccessRelationship"
          href="AccessRelationship_f70a6f48.xml#f70a6f48"/>
    </sourceConnections>
    <sourceConnections
        xsi:type="archimate:DiagramModelArchimateConnection"
        id="4d05e11f"
        source="db8eb96a"
        target="bac485e3">
      <archimateRelationship
          xsi:type="archimate:AccessRelationship"
          href="AccessRelationship_9e57e1cb.xml#9e57e1cb"/>
    </sourceConnections>
    <bounds
        x="228"
        y="228"
        width="120"
        height="55"/>
    <archimateElement
        xsi:type="archimate:BusinessFunction"
        href="BusinessFunction_680e6396.xml#680e6396"/>
  </children>
  <children
      xsi:type="archimate:DiagramModelArchimateObject"
      id="bc8ad119"
      targetConnections="72cfcf8c">
    <bounds
        x="924"
        y="372"
        width="120"
        height="55"/>
    <archimateElement
        xsi:type="archimate:BusinessObject"
        href="BusinessObject_3c002486.xml#3c002486"/>
  </children>
  <children
      xsi:type="archimate:DiagramModelArchimateObject"
      id="57b9b81b"
      targetConnections="2c543b19 1f62629d">
    <bounds
        x="672"
        y="528"
        width="120"
        height="55"/>
    <archimateElement
        xsi:type="archimate:BusinessObject"
        href="BusinessObject_72c196d8.xml#72c196d8"/>
  </children>
  <children
      xsi:type="archimate:DiagramModelArchimateObject"
      id="a2fc3905"
      targetConnections="d73efcd3 f892cc04">
    <bounds
        x="432"
        y="444"
        width="120"
        height="55"/>
    <archimateElement
        xsi:type="archimate:BusinessObject"
        href="BusinessObject_09c14e6f.xml#09c14e6f"/>
  </children>
  <children
      xsi:type="archimate:DiagramModelArchimateObject"
      id="20feb05c"
      targetConnections="2acfde97">
    <bounds
        x="864"
        y="336"
        width="120"
        height="55"/>
    <archimateElement
        xsi:type="archimate:BusinessObject"
        href="BusinessObject_ece401fd.xml#ece401fd"/>
  </children>
  <children
      xsi:type="archimate:DiagramModelArchimateObject"
      id="9727ca1f">
    <sourceConnections
        xsi:type="archimate:DiagramModelArchimateConnection"
        id="f892cc04"
        source="9727ca1f"
        target="a2fc3905">
      <archimateRelationship
          xsi:type="archimate:AccessRelationship"
          href="AccessRelationship_92348bb9.xml#92348bb9"/>
    </sourceConnections>
    <sourceConnections
        xsi:type="archimate:DiagramModelArchimateConnection"
        id="c7cc8016"
        source="9727ca1f"
        target="c9048919">
      <archimateRelationship
          xsi:type="archimate:AccessRelationship"
          href="AccessRelationship_5374d69b.xml#5374d69b"/>
    </sourceConnections>
    <sourceConnections
        xsi:type="archimate:DiagramModelArchimateConnection"
        id="1f62629d"
        source="9727ca1f"
        target="57b9b81b">
      <archimateRelationship
          xsi:type="archimate:AccessRelationship"
          href="AccessRelationship_bb2a8163.xml#bb2a8163"/>
    </sourceConnections>
    <sourceConnections
        xsi:type="archimate:DiagramModelArchimateConnection"
        id="ae68d628"
        source="9727ca1f"
        target="7e8c4fa1">
      <archimateRelationship
          xsi:type="archimate:AccessRelationship"
          href="AccessRelationship_04543949.xml#04543949"/>
    </sourceConnections>
    <sourceConnections
        xsi:type="archimate:DiagramModelArchimateConnection"
        id="ae84f0ef"
        source="9727ca1f"
        target="f7d74d55">
      <archimateRelationship
          xsi:type="archimate:AccessRelationship"
          href="AccessRelationship_cac80ac5.xml#cac80ac5"/>
    </sourceConnections>
    <sourceConnections
        xsi:type="archimate:DiagramModelArchimateConnection"
        id="22086808"
        source="9727ca1f"
        target="5abf0169">
      <archimateRelationship
          xsi:type="archimate:AccessRelationship"
          href="AccessRelationship_8dbbe22f.xml#8dbbe22f"/>
    </sourceConnections>
    <bounds
        x="516"
        y="564"
        width="120"
        height="55"/>
    <archimateElement
        xsi:type="archimate:BusinessRole"
        href="BusinessRole_6180bd09.xml#6180bd09"/>
  </children>
  <children
      xsi:type="archimate:DiagramModelArchimateObject"
      id="c9048919"
      targetConnections="c7cc8016 46dbc141">
    <bounds
        x="360"
        y="528"
        width="120"
        height="55"/>
    <archimateElement
        xsi:type="archimate:BusinessObject"
        href="BusinessObject_72c196d8.xml#72c196d8"/>
  </children>
  <children
      xsi:type="archimate:DiagramModelArchimateObject"
      id="7e8c4fa1"
      targetConnections="87508bf8 ae68d628">
    <bounds
        x="360"
        y="600"
        width="120"
        height="55"/>
    <archimateElement
        xsi:type="archimate:BusinessObject"
        href="BusinessObject_dbad645d.xml#dbad645d"/>
  </children>
  <children
      xsi:type="archimate:DiagramModelArchimateObject"
      id="f7d74d55"
      targetConnections="ae84f0ef 3b25227f">
    <bounds
        x="672"
        y="600"
        width="120"
        height="55"/>
    <archimateElement
        xsi:type="archimate:BusinessObject"
        href="BusinessObject_dbad645d.xml#dbad645d"/>
  </children>
  <children
      xsi:type="archimate:DiagramModelArchimateObject"
      id="5abf0169"
      targetConnections="22086808 af8fd987">
    <bounds
        x="600"
        y="444"
        width="120"
        height="55"/>
    <archimateElement
        xsi:type="archimate:BusinessObject"
        href="BusinessObject_28c7a999.xml#28c7a999"/>
  </children>
  <children
      xsi:type="archimate:DiagramModelArchimateObject"
      id="bac485e3"
      targetConnections="4d05e11f edf6af78">
    <bounds
        x="360"
        y="294"
        width="120"
        height="55"/>
    <archimateElement
        xsi:type="archimate:BusinessObject"
        href="BusinessObject_bb670f3f.xml#bb670f3f"/>
  </children>
</archimate:ArchimateDiagramModel>
