<archimate:ArchimateDiagramModel
    xmlns:xsi="http://www.w3.org/2001/XMLSchema-instance"
    xmlns:archimate="http://www.archimatetool.com/archimate"
    name="20170511 Principe ieder z'n eigen system"
    id="aa6721a9">
  <children
      xsi:type="archimate:DiagramModelArchimateObject"
      id="bfdbafe1"
      targetConnections="d7d17199">
    <bounds
        x="480"
        y="68"
        width="120"
        height="55"/>
    <archimateElement
        xsi:type="archimate:BusinessActor"
        href="BusinessActor_71cd81be.xml#71cd81be"/>
  </children>
  <children
      xsi:type="archimate:DiagramModelArchimateObject"
      id="26bad108"
      targetConnections="382dfc64">
    <bounds
        x="324"
        y="68"
        width="120"
        height="55"/>
    <archimateElement
        xsi:type="archimate:BusinessActor"
        href="BusinessActor_280eee9f.xml#280eee9f"/>
  </children>
  <children
      xsi:type="archimate:DiagramModelArchimateObject"
      id="d783d3bc">
    <sourceConnections
        xsi:type="archimate:DiagramModelArchimateConnection"
        id="382dfc64"
        source="d783d3bc"
        target="26bad108">
      <archimateRelationship
          xsi:type="archimate:ServingRelationship"
          href="ServingRelationship_3cb7943c.xml#3cb7943c"/>
    </sourceConnections>
    <bounds
        x="324"
        y="192"
        width="120"
        height="55"/>
    <archimateElement
        xsi:type="archimate:ApplicationComponent"
        href="ApplicationComponent_3873da5d.xml#3873da5d"/>
  </children>
  <children
      xsi:type="archimate:DiagramModelArchimateObject"
      id="8ce9c6f0">
    <sourceConnections
        xsi:type="archimate:DiagramModelArchimateConnection"
        id="d7d17199"
        source="8ce9c6f0"
        target="bfdbafe1">
      <archimateRelationship
          xsi:type="archimate:ServingRelationship"
          href="ServingRelationship_49e78605.xml#49e78605"/>
    </sourceConnections>
    <bounds
        x="480"
        y="192"
        width="120"
        height="55"/>
    <archimateElement
        xsi:type="archimate:ApplicationComponent"
        href="ApplicationComponent_49bfbe20.xml#49bfbe20"/>
  </children>
  <children
      xsi:type="archimate:DiagramModelArchimateObject"
      id="c8e8f99a">
    <sourceConnections
        xsi:type="archimate:DiagramModelArchimateConnection"
        id="440d925d"
        source="c8e8f99a"
        target="5b7c8884">
      <archimateRelationship
          xsi:type="archimate:ServingRelationship"
          href="ServingRelationship_36bfda30.xml#36bfda30"/>
    </sourceConnections>
    <bounds
        x="172"
        y="192"
        width="120"
        height="55"/>
    <archimateElement
        xsi:type="archimate:ApplicationComponent"
        href="ApplicationComponent_49bfbe20.xml#49bfbe20"/>
  </children>
  <children
      xsi:type="archimate:DiagramModelArchimateObject"
      id="5b7c8884"
      targetConnections="440d925d">
    <bounds
        x="172"
        y="68"
        width="129"
        height="55"/>
    <archimateElement
        xsi:type="archimate:BusinessActor"
        href="BusinessActor_653aab08.xml#653aab08"/>
  </children>
</archimate:ArchimateDiagramModel>
